interactions/ext/autosharder/__init__.py
interactions/ext/autosharder/_setup.py
interactions/ext/autosharder/dummy.py
interactions_autosharder-2.1.1.dist-info/LICENSE
interactions_autosharder-2.1.1.dist-info/METADATA
interactions_autosharder-2.1.1.dist-info/WHEEL
interactions_autosharder-2.1.1.dist-info/top_level.txt
interactions_autosharder-2.1.1.dist-info/RECORD
