Metadata-Version: 2.1
Name: interactions-autosharder
Version: 2.1.1
Summary: Autosharder for interactions.py
Home-page: https://github.com/EdVraz/interactions-autosharder
Author: EdVraz
Author-email: edvraz12@gmail.com
License: MIT
Classifier: Programming Language :: Python :: 3
Classifier: Development Status :: 4 - Beta
Classifier: License :: OSI Approved :: MIT License
Classifier: Operating System :: OS Independent
License-File: LICENSE
Requires-Dist: discord-py-interactions (>=4.3.4)
